httpx_qs/__init__.py
httpx_qs/py.typed
httpx_qs/enums/merge_policy.py
httpx_qs/transporters/smart_query_strings.py
httpx_qs/utils/merge_query.py
httpx_qs-0.2.1.dist-info/METADATA
httpx_qs-0.2.1.dist-info/WHEEL
httpx_qs-0.2.1.dist-info/licenses/LICENSE
httpx_qs-0.2.1.dist-info/RECORD
